{
  "DIA_Miltia_QM401_FOUNDSOMETHING_03_01": "Доповідаю, я виявив щось підозріле біля нижнього входу в печеру.",
  "DIA_Miltia_QM401_WATERFALL_03_01": "Саме тут я знайшов цю записку, але, на жаль, вона мало про що говорить.",
  "DIA_Miltia_QM401_WATERFALL_03_02": "Можливо, ти зможеш її розшифрувати.",
  "DIA_Miltia_QM401_LETTER_03_01": "І як, тобі вдалося щось зрозуміти з цієї тарабарщини?",
  "DIA_Miltia_QM401_LETTER_15_01": "Так, хтось хоче зустрітися зі мною без свідків. Я подбаю про це, а ти перевір решту печери.",
  "DIA_Miltia_QM401_LETTER_15_02": "Ні, ця записка не має жодного сенсу. Я ще раз роздивлюся тут, а ти поки перевір решту печери.",
  "TRIA_MIL_13513_Militia_QM401_Nothing_03_01": "Ані сліду відступників, але я знайшов наших розвідників.",
  "DIA_Miltia_QM401_LETTER_Yes_Choice": "Так, хтось хоче зустрітися зі мною без свідків...",
  "DIA_Miltia_QM401_LETTER_No_Choice": "Ні, ця записка не має жодного сенсу..."
}