{
  "DIA_Broddy_EXIT_15_01": "Насправді, мені вже час йти.",
  "DIA_Broddy_EXIT_03_02": "Правильне рішення.",
  "DIA_Broddy_AmbientBeforeJoin_03_01": "На що витріщився, виродку?",
  "DIA_Broddy_AmbientBeforeJoin_03_02": "Я стежу за тобою, шмаркачу.",
  "DIA_Broddy_Q205_AllDay_15_01": "Ти що, цілий день тут сидиш?",
  "DIA_Broddy_Q205_AllDay_03_02": "Так.",
  "DIA_Broddy_Q205_Move_15_01": "Тобі часом нікуди не треба?",
  "DIA_Broddy_Q205_Move_03_02": "Ні.",
  "DIA_Broddy_Q205_Salvi_15_01": "Навіть якщо Сальві накаже тобі?",
  "DIA_Broddy_Q205_Salvi_03_02": "Тоді це інша справа...",
  "DIA_Broddy_Q205_Salvi_03_03": "Так чи інакше, забирайся геть з моїх очей і дай мені спокійно доїсти цей огидний черствий хліб.",
  "DIA_Broddy_Q205_Hungry_15_01": "Я думав, що у вас досить багато запасів.",
  "DIA_Broddy_Q205_Hungry_03_02": "Справа ось у чому! У нас є кілька ящиків, але Сальві забороняє мені нормально харчуватися, бо я, за його словами, жеру як кротощур.",
  "DIA_Broddy_Q205_Hungry_03_03": "За його словами, ще трохи – і я не зможу навіть битися. Та що він взагалі знає!",
  "DIA_Broddy_Q205_Hungry_03_04": "Коли ми жили в казармах, їжа була жахливою, а тепер, коли у нас є хороша їжа, він не дає мені її!",
  "DIA_Broddy_Q205_Smell_03_01": "Відчуваєш запах? Це хтось приготував рагу?",
  "DIA_Broddy_Q205_Smell_15_02": "Так, ми щойно приготували його в печері з ящиками.",
  "DIA_Broddy_Q205_Smell_15_03": "Ось, спробуй.",
  "DIA_Broddy_Q205_Smell_15_04": "Якщо поспішиш, можливо, для тебе ще щось залишиться.",
  "DIA_Broddy_Q205_Smell_03_05": "От холера, я більше не можу тут сидіти, я МУШУ поїсти чогось нормального!",
  "DIA_Broddy_QM401_Fight_03_01": "Так-так, хто тут у нас?",
  "DIA_Broddy_QM401_Fight_03_02": "Берто, ах ти зрадник, я віднесу твою голову Сальві!",
  "DIA_Broddy_QM401_Fight_Traitor_15_01": "Хіба є зрадником той, хто зраджує зрадників?",
  "DIA_Broddy_QM401_Fight_Traitor_03_02": "Про що ти говориш? Ну вас до біса!"
}